orbital_quay/__init__.py
orbital_quay/status_1.py
orbital_quay/_clique/__init__.py
orbital_quay/_clique/group/__init__.py
orbital_quay/_licenses/gpl-3.0-standalone.html
orbital_quay/_status/status.proc.py
orbital_quay-1.0.0.dist-info/METADATA
orbital_quay-1.0.0.dist-info/WHEEL
orbital_quay-1.0.0.dist-info/top_level.txt
orbital_quay-1.0.0.dist-info/RECORD
