Metadata-Version: 2.1
Name: orbital_quay
Version: 1.0.0
Summary: docker logistics
Keywords: docker
Requires-Dist: bracelet
Requires-Dist: carbonado
Requires-Dist: click
